langevals_core/base_evaluator.py
langevals_core/litellm_patch.py
langevals_core/utils.py
langevals_core-0.1.18.dist-info/METADATA
langevals_core-0.1.18.dist-info/WHEEL
langevals_core-0.1.18.dist-info/RECORD
