Metadata-Version: 2.4
Name: langevals-core
Version: 0.1.18
Summary: Core package for LLM evaluation platform, providing base classes and utilities.
License: MIT
Author: Rogerio Chaves
Author-email: rogerio@langwatch.ai
Requires-Python: >=3.11,<4.0
Classifier: License :: OSI Approved :: MIT License
Classifier: Programming Language :: Python :: 3
Classifier: Programming Language :: Python :: 3.11
Classifier: Programming Language :: Python :: 3.12
Classifier: Programming Language :: Python :: 3.13
Classifier: Programming Language :: Python :: 3.14
Requires-Dist: anyio (>=4.8.0,<5.0.0)
Requires-Dist: boto3 (>=1.34.34,<2.0.0)
Requires-Dist: litellm (==1.76.0)
Requires-Dist: openai (>=1.107.0,<2.0.0)
Requires-Dist: pandas (>=2.2.2,<3.0.0)
Requires-Dist: pydantic (>=2.4.0,<3.0.0)
Requires-Dist: tenacity (>=8.4.0,<9.0.0)
Requires-Dist: tqdm (>=4.66.4,<5.0.0)
Requires-Dist: transformers (>=4.49.0,<5.0.0)
Requires-Dist: vertexai (>=1.71.1,<2.0.0)
